data_understand/__init__.py
data_understand/constants.py
data_understand/input_validations.py
data_understand/jupyter_notebook_generator.py
data_understand/main.py
data_understand/messages.py
data_understand/pdf_generator.py
data_understand/utils.py
data_understand/version.py
data_understand/class_imbalance/__init__.py
data_understand/class_imbalance/imbalance.py
data_understand/dataset_characteristics/__init__.py
data_understand/dataset_characteristics/characteristics.py
data_understand/dataset_statistics/__init__.py
data_understand/dataset_statistics/statistics.py
data_understand/feature_correlation/__init__.py
data_understand/feature_correlation/correlation.py
data_understand/load_dataset/__init__.py
data_understand/load_dataset/dataset.py
data_understand/target_characteristics/__init__.py
data_understand/target_characteristics/target.py
data_understand/value_distributions/__init__.py
data_understand/value_distributions/box_plot_distribution.py
data_understand/value_distributions/cat_frequency_distribution.py
data_understand/value_distributions/histogram_distribution.py
data_understand-0.0.6.dist-info/LICENSE
data_understand-0.0.6.dist-info/METADATA
data_understand-0.0.6.dist-info/WHEEL
data_understand-0.0.6.dist-info/entry_points.txt
data_understand-0.0.6.dist-info/top_level.txt
data_understand-0.0.6.dist-info/RECORD
