Metadata-Version: 2.1
Name: data-understand
Version: 0.0.6
Summary: Utility package for generating insights for datasets
Home-page: https://github.com/ggupta2005/data.understand
Author: Gaurav Gupta
Author-email: ggupta2005@gmail.com
Classifier: Programming Language :: Python :: 3.7
Classifier: Programming Language :: Python :: 3.8
Classifier: Programming Language :: Python :: 3.9
Classifier: Programming Language :: Python :: 3.10
Classifier: Programming Language :: Python :: 3.11
Classifier: License :: OSI Approved :: MIT License
Classifier: Operating System :: OS Independent
Classifier: Development Status :: 3 - Alpha
Requires-Python: >=3.6
License-File: LICENSE
Requires-Dist: pandas <2.0.0
Requires-Dist: nbformat
Requires-Dist: matplotlib
Requires-Dist: numpy
Requires-Dist: fpdf2
Requires-Dist: seaborn
Requires-Dist: raiutils
